{
 "actions": [],
 "allow_rename": 1,
 "creation": "2024-10-17 09:32:44.266003",
 "doctype": "DocType",
 "editable_grid": 1,
 "engine": "InnoDB",
 "field_order": [
  "date",
  "on_air_date_and_time",
  "subject",
  "title"
 ],
 "fields": [
  {
   "fieldname": "date",
   "fieldtype": "Date",
   "in_list_view": 1,
   "label": "Date"
  },
  {
   "fieldname": "on_air_date_and_time",
   "fieldtype": "Datetime",
   "in_list_view": 1,
   "label": "On Air Date and Time"
  },
  {
   "fieldname": "subject",
   "fieldtype": "Data",
   "in_list_view": 1,
   "label": "Subject"
  },
  {
   "fieldname": "title",
   "fieldtype": "Data",
   "in_list_view": 1,
   "label": "Title"
  }
 ],
 "index_web_pages_for_search": 1,
 "istable": 1,
 "links": [],
 "modified": "2024-10-17 09:37:30.537112",
 "modified_by": "Administrator",
 "module": "BEAMS",
 "name": "Stringer Bill Detail",
 "owner": "Administrator",
 "permissions": [],
 "sort_field": "modified",
 "sort_order": "DESC",
 "states": []
}